README.rst
setup.cfg
setup.py
jelly/__init__.py
jelly/config.py
jelly/ics.py
jelly/id_assign.py
jelly/model.py
jelly/util.py
jelly/vector.py
jelly/wrapper.py
jelly.egg-info/PKG-INFO
jelly.egg-info/SOURCES.txt
jelly.egg-info/dependency_links.txt
jelly.egg-info/requires.txt
jelly.egg-info/top_level.txt