Metadata-Version: 1.0
Name: jelly
Version: 0.1.0
Summary: Abstraction layer for running numerical hydrodynamics software
Home-page: UNKNOWN
Author: Eduard Bopp
Author-email: eduard.bopp@aepsil0n.de
License: UNKNOWN
Platform: UNKNOWN
